task_queue-2.14.2.dist-info/licenses/AUTHORS
task_queue-2.14.2.dist-info/licenses/LICENSE
taskqueue/__init__.py
taskqueue/aws_queue_api.py
taskqueue/file_queue_api.py
taskqueue/goog_pubsub_api.py
taskqueue/lib.py
taskqueue/paths.py
taskqueue/queueablefns.py
taskqueue/queueables.py
taskqueue/registered_task.py
taskqueue/scheduler.py
taskqueue/secrets.py
taskqueue/taskqueue.py
taskqueue/threaded_queue.py
taskqueue_cli/LICENSE
taskqueue_cli/__init__.py
taskqueue_cli/taskqueue_cli.py
task_queue-2.14.2.dist-info/METADATA
task_queue-2.14.2.dist-info/WHEEL
task_queue-2.14.2.dist-info/entry_points.txt
task_queue-2.14.2.dist-info/pbr.json
task_queue-2.14.2.dist-info/top_level.txt
task_queue-2.14.2.dist-info/RECORD
