Metadata-Version: 2.4
Name: task-queue
Version: 2.14.2
Summary: Multithreaded cloud queue client.
Home-page: https://github.com/seung-lab/python-task-queue/
Author: Ignacio Tartavull, William Silversmith, and others
Author-email: ws9@princeton.edu
License: BSD
Classifier: Intended Audience :: Developers
Classifier: Development Status :: 5 - Production/Stable
Classifier: License :: OSI Approved :: BSD License
Classifier: Programming Language :: Python
Classifier: Programming Language :: Python :: 3
Classifier: Programming Language :: Python :: 3.5
Classifier: Programming Language :: Python :: 3.6
Classifier: Programming Language :: Python :: 3.7
Classifier: Programming Language :: Python :: 3.8
Classifier: Topic :: Utilities
License-File: LICENSE
License-File: AUTHORS
Requires-Dist: boto3
Requires-Dist: click
Requires-Dist: gevent
Requires-Dist: google-auth>=1.10.0
Requires-Dist: google-cloud-core>=1.1.0
Requires-Dist: orjson
Requires-Dist: numpy>=1.13.1
Requires-Dist: pathos
Requires-Dist: pbr
Requires-Dist: tenacity>=8.0.1
Requires-Dist: tqdm
Requires-Dist: requests<3,>2
Dynamic: author
Dynamic: author-email
Dynamic: classifier
Dynamic: description
Dynamic: description-content-type
Dynamic: home-page
Dynamic: license
Dynamic: license-file
Dynamic: requires-dist
Dynamic: summary
